ExodusDecoderss.py
exodusdecoderss-1.4.4.dist-info/LICENSE
exodusdecoderss-1.4.4.dist-info/METADATA
exodusdecoderss-1.4.4.dist-info/WHEEL
exodusdecoderss-1.4.4.dist-info/RECORD
